tilejson/__init__.py
tilejson/cli.py
tilejson/templates/index.html
tilejson/templates/index_nogeo.html
tilejson-0.1.1.dist-info/METADATA
tilejson-0.1.1.dist-info/WHEEL
tilejson-0.1.1.dist-info/entry_points.txt
tilejson-0.1.1.dist-info/licenses/LICENSE
tilejson-0.1.1.dist-info/RECORD
