Metadata-Version: 2.1
Name: tilejson
Version: 0.1.1
Summary: Create simple map viewer from TileJSON URL
Project-URL: Source, https://github.com/developmentseed/tilejson
Author-email: Vincent Sarago <vincent@developmentseed.com>
License: MIT License
License-File: LICENSE
Classifier: Intended Audience :: Information Technology
Classifier: Intended Audience :: Science/Research
Classifier: License :: OSI Approved :: BSD License
Classifier: Programming Language :: Python :: 3.8
Classifier: Programming Language :: Python :: 3.9
Classifier: Programming Language :: Python :: 3.10
Classifier: Programming Language :: Python :: 3.11
Classifier: Topic :: Scientific/Engineering :: GIS
Requires-Python: >=3.8
Requires-Dist: click
Requires-Dist: importlib-resources>=1.1.0; python_version < '3.9'
Requires-Dist: jinja2<4.0.0,>=2.11.2
Requires-Dist: starlette
Provides-Extra: dev
Requires-Dist: pre-commit; extra == 'dev'
Provides-Extra: test
Requires-Dist: pytest; extra == 'test'
Requires-Dist: pytest-cov; extra == 'test'
